{
  "@id": "/@@sessoes/id/1688",
  "@id_presenca": "/@@sessoes/id/1688/presenca",
  "@id_votacao": "/@@sessoes/id/1688/votacao",
  "@type": "SessaoPlenaria",
  "ata": [
    {
      "content-type": "application/pdf",
      "download": "/@@sapl_documentos_download?path=ata_sessao/1688_ata_sessao.pdf",
      "filename": "1688_ata_sessao.pdf",
      "size": ""
    }
  ],
  "date": "2026-05-04",
  "description": "1ª Reunião Ordinária - 04/05/2026",
  "endTime": "",
  "id": "1688",
  "pauta": [
    {
      "content-type": "application/pdf",
      "download": "/@@sapl_documentos_download?path=pauta_sessao/1688_pauta_sessao.pdf",
      "filename": "1688_pauta_sessao.pdf",
      "size": ""
    }
  ],
  "startTime": "09:00",
  "title": "1ª Reunião Ordinária",
  "type": "Ordinária",
  "type_id": 1
}