{
  "@id": "/@@materias/205276",
  "@type": "Materia",
  "accessoryDocument": [],
  "amendment": [],
  "attached": [],
  "authorship": [
    {
      "description": "Parlamentar",
      "firstAuthor": true,
      "title": "Liza Prado (CIDADANIA)"
    }
  ],
  "committeeOpinion": [],
  "date": "2025-01-24",
  "description": "Tapa buraco Rua Boa Esperança, próximo ao n° 250 - B. Granada.",
  "file": [
    {
      "content-type": "application/pdf",
      "download": "/@@sapl_documentos_download?path=materia/205276_texto_integral.pdf",
      "filename": "205276_texto_integral.pdf",
      "size": "108.7 KB"
    }
  ],
  "id": "205276",
  "inProgress": false,
  "permissions": {
    "canAddDocument": false,
    "canTramitar": false,
    "showAcompanhar": false,
    "showPastaDigital": true,
    "tramitarModalUrl": ""
  },
  "processing": [
    {
      "date": "2025-02-04 13:49:44",
      "deadline": null,
      "description": "",
      "destinationUnit": "Arquivo",
      "file": [
        {
          "content-type": "application/pdf",
          "download": "/@@sapl_documentos_download?path=materia/tramitacao/547149_tram.pdf",
          "filename": "547149_tram.pdf",
          "size": "21.2 KB"
        }
      ],
      "last": true,
      "sourceUnit": "Seção de Controle de Processo Legislativo",
      "title": "Arquivado"
    },
    {
      "date": "2025-02-03 15:32:21",
      "deadline": null,
      "description": "",
      "destinationUnit": "Seção de Controle de Processo Legislativo",
      "file": [
        {
          "content-type": "application/pdf",
          "download": "/@@sapl_documentos_download?path=materia/tramitacao/539339_tram.pdf",
          "filename": "539339_tram.pdf",
          "size": "21.2 KB"
        }
      ],
      "last": false,
      "sourceUnit": "Plenário",
      "title": "Aprovado"
    },
    {
      "date": "2025-01-27 11:34:08",
      "deadline": null,
      "description": "",
      "destinationUnit": "Plenário",
      "file": [
        {
          "content-type": "application/pdf",
          "download": "/@@sapl_documentos_download?path=materia/tramitacao/533233_tram.pdf",
          "filename": "533233_tram.pdf",
          "size": "21.3 KB"
        }
      ],
      "last": false,
      "sourceUnit": "Departamento Técnico Legislativo",
      "title": "Incluído na Pauta - Requerimento/Indicação/Moção/Pedido Inf"
    },
    {
      "date": "2025-01-24 12:46:58",
      "deadline": null,
      "description": "<p>Proposição eletrônica enviada em 22/01/2025 11:01:46. Matéria incorporada em 24/01/2025 12:46:58 sob protocolo nº 816/2025</p>",
      "destinationUnit": "Departamento Técnico Legislativo",
      "file": [
        {
          "content-type": "application/pdf",
          "download": "/@@sapl_documentos_download?path=materia/tramitacao/532130_tram.pdf",
          "filename": "532130_tram.pdf",
          "size": "21.4 KB"
        }
      ],
      "last": false,
      "sourceUnit": "Protocolo Eletrônico",
      "title": "Recebimento no Protocolo"
    }
  ],
  "processingRegime": "Ordinário",
  "processingRegime_id": "1",
  "protocol": "816/2025",
  "quorum": "Maioria simples",
  "quorum_id": "1",
  "remoteUrl": "/consultas/materia/materia_mostrar_proc?cod_materia=205276",
  "substitute": [],
  "title": "Requerimento nº 723/2025",
  "voteResult": [
    {
      "@id": "/@@sessoes/1497",
      "cod_ordem": 235959,
      "cod_sessao_plen": 1497,
      "date": "2025-02-03",
      "description": "Expediente da 1ª Reunião Ordinária",
      "result": [
        {
          "absent": 0,
          "abstention": 0,
          "contrary": 0,
          "favorable": 0
        }
      ],
      "resultModalUrl": "/consultas/sessao_plenaria/sessao_plenaria_mostrar_painel_proc?cod_sessao_plen=1497&cod_ordem=235959&cod_materia=205276&tipo_materia=expediente&modal=1",
      "title": "Aprovado",
      "turn": "",
      "votingType": "Simbólica"
    }
  ]
}