{
  "@id": "/@@materias/210421",
  "@type": "Materia",
  "accessoryDocument": [],
  "amendment": [],
  "attached": [],
  "authorship": [
    {
      "description": "Parlamentar",
      "firstAuthor": true,
      "title": "Abatenio Marquez (PP)"
    }
  ],
  "committeeOpinion": [],
  "date": "2025-03-07",
  "description": "complementação do calçamento no entorno do Poliesportivo do Jardim América, em especial de frente à Rua Adão Elias Rodrigues, próximo nº 154, urgente! CEP 38401-776 - bairro Santa Rosa",
  "file": [
    {
      "content-type": "application/pdf",
      "download": "/@@sapl_documentos_download?path=materia/210421_texto_integral.pdf",
      "filename": "210421_texto_integral.pdf",
      "size": "1.7 MB"
    }
  ],
  "id": "210421",
  "inProgress": false,
  "permissions": {
    "canAddDocument": false,
    "canTramitar": false,
    "showAcompanhar": false,
    "showPastaDigital": true,
    "tramitarModalUrl": ""
  },
  "processing": [
    {
      "date": "2025-03-10 13:20:29",
      "deadline": null,
      "description": "",
      "destinationUnit": "Arquivo",
      "file": [
        {
          "content-type": "application/pdf",
          "download": "/@@sapl_documentos_download?path=materia/tramitacao/563727_tram.pdf",
          "filename": "563727_tram.pdf",
          "size": "21.3 KB"
        }
      ],
      "last": true,
      "sourceUnit": "Seção de Controle de Processo Legislativo",
      "title": "Arquivado"
    },
    {
      "date": "2025-03-10 11:55:28",
      "deadline": null,
      "description": "",
      "destinationUnit": "Seção de Controle de Processo Legislativo",
      "file": [
        {
          "content-type": "application/pdf",
          "download": "/@@sapl_documentos_download?path=materia/tramitacao/563633_tram.pdf",
          "filename": "563633_tram.pdf",
          "size": "21.3 KB"
        }
      ],
      "last": false,
      "sourceUnit": "Plenário",
      "title": "Aprovado"
    },
    {
      "date": "2025-03-07 13:44:07",
      "deadline": null,
      "description": "",
      "destinationUnit": "Plenário",
      "file": [
        {
          "content-type": "application/pdf",
          "download": "/@@sapl_documentos_download?path=materia/tramitacao/561347_tram.pdf",
          "filename": "561347_tram.pdf",
          "size": "21.4 KB"
        }
      ],
      "last": false,
      "sourceUnit": "Departamento Técnico Legislativo",
      "title": "Incluído na Pauta - Requerimento/Indicação/Moção/Pedido Inf"
    },
    {
      "date": "2025-03-07 13:42:18",
      "deadline": null,
      "description": "<p>Proposição eletrônica enviada em 07/03/2025 13:36:54. Matéria incorporada em 07/03/2025 13:42:18 sob protocolo nº 5932/2025</p>",
      "destinationUnit": "Departamento Técnico Legislativo",
      "file": [
        {
          "content-type": "application/pdf",
          "download": "/@@sapl_documentos_download?path=materia/tramitacao/561341_tram.pdf",
          "filename": "561341_tram.pdf",
          "size": "21.5 KB"
        }
      ],
      "last": false,
      "sourceUnit": "Protocolo Eletrônico",
      "title": "Recebimento no Protocolo"
    }
  ],
  "processingRegime": "Ordinário",
  "processingRegime_id": "1",
  "protocol": "5932/2025",
  "quorum": "Maioria simples",
  "quorum_id": "1",
  "remoteUrl": "/consultas/materia/materia_mostrar_proc?cod_materia=210421",
  "substitute": [],
  "title": "Requerimento nº 5455/2025",
  "voteResult": [
    {
      "@id": "/@@sessoes/1512",
      "cod_ordem": 240836,
      "cod_sessao_plen": 1512,
      "date": "2025-03-10",
      "description": "Expediente da 1ª Reunião Ordinária",
      "result": [
        {
          "absent": 0,
          "abstention": 0,
          "contrary": 0,
          "favorable": 0
        }
      ],
      "resultModalUrl": "/consultas/sessao_plenaria/sessao_plenaria_mostrar_painel_proc?cod_sessao_plen=1512&cod_ordem=240836&cod_materia=210421&tipo_materia=expediente&modal=1",
      "title": "Aprovado",
      "turn": "",
      "votingType": "Simbólica"
    }
  ]
}