{
  "@id": "/@@materias/214660",
  "@type": "Materia",
  "accessoryDocument": [],
  "amendment": [],
  "attached": [],
  "authorship": [
    {
      "description": "Parlamentar",
      "firstAuthor": true,
      "title": "Ângela Do Postinho (Solidariedade)"
    }
  ],
  "committeeOpinion": [],
  "date": "2025-04-07",
  "description": "que seja feito a manutenção e implantação de mas poste bairro bela vista Canaã todos as ruas da b1 ate b5",
  "file": [
    {
      "content-type": "application/pdf",
      "download": "/@@sapl_documentos_download?path=materia/214660_texto_integral.pdf",
      "filename": "214660_texto_integral.pdf",
      "size": "95.7 KB"
    }
  ],
  "id": "214660",
  "inProgress": false,
  "permissions": {
    "canAddDocument": false,
    "canTramitar": false,
    "showAcompanhar": false,
    "showPastaDigital": true,
    "tramitarModalUrl": ""
  },
  "processing": [
    {
      "date": "2025-04-08 12:34:48",
      "deadline": null,
      "description": "",
      "destinationUnit": "Arquivo",
      "file": [
        {
          "content-type": "application/pdf",
          "download": "/@@sapl_documentos_download?path=materia/tramitacao/588500_tram.pdf",
          "filename": "588500_tram.pdf",
          "size": "21.2 KB"
        }
      ],
      "last": true,
      "sourceUnit": "Seção de Controle de Processo Legislativo",
      "title": "Arquivado"
    },
    {
      "date": "2025-04-08 11:00:43",
      "deadline": null,
      "description": "",
      "destinationUnit": "Seção de Controle de Processo Legislativo",
      "file": [
        {
          "content-type": "application/pdf",
          "download": "/@@sapl_documentos_download?path=materia/tramitacao/588250_tram.pdf",
          "filename": "588250_tram.pdf",
          "size": "21.3 KB"
        }
      ],
      "last": false,
      "sourceUnit": "Plenário",
      "title": "Aprovado"
    },
    {
      "date": "2025-04-07 14:25:26",
      "deadline": null,
      "description": "",
      "destinationUnit": "Plenário",
      "file": [
        {
          "content-type": "application/pdf",
          "download": "/@@sapl_documentos_download?path=materia/tramitacao/587938_tram.pdf",
          "filename": "587938_tram.pdf",
          "size": "21.3 KB"
        }
      ],
      "last": false,
      "sourceUnit": "Departamento Técnico Legislativo",
      "title": "Incluído na Pauta - Requerimento/Indicação/Moção/Pedido Inf"
    },
    {
      "date": "2025-04-07 13:52:31",
      "deadline": null,
      "description": "<p>Proposição eletrônica enviada em 07/04/2025 10:50:10. Matéria incorporada em 07/04/2025 13:52:31 sob protocolo nº 10143/2025</p>",
      "destinationUnit": "Departamento Técnico Legislativo",
      "file": [
        {
          "content-type": "application/pdf",
          "download": "/@@sapl_documentos_download?path=materia/tramitacao/587401_tram.pdf",
          "filename": "587401_tram.pdf",
          "size": "21.4 KB"
        }
      ],
      "last": false,
      "sourceUnit": "Protocolo Eletrônico",
      "title": "Recebimento no Protocolo"
    }
  ],
  "processingRegime": "Ordinário",
  "processingRegime_id": "1",
  "protocol": "10143/2025",
  "quorum": "Maioria simples",
  "quorum_id": "1",
  "remoteUrl": "/consultas/materia/materia_mostrar_proc?cod_materia=214660",
  "substitute": [],
  "title": "Requerimento nº 9379/2025",
  "voteResult": [
    {
      "@id": "/@@sessoes/1529",
      "cod_ordem": 245163,
      "cod_sessao_plen": 1529,
      "date": "2025-04-08",
      "description": "Expediente da 6ª Reunião Ordinária",
      "result": [
        {
          "absent": 0,
          "abstention": 0,
          "contrary": 0,
          "favorable": 0
        }
      ],
      "resultModalUrl": "/consultas/sessao_plenaria/sessao_plenaria_mostrar_painel_proc?cod_sessao_plen=1529&cod_ordem=245163&cod_materia=214660&tipo_materia=expediente&modal=1",
      "title": "Aprovado",
      "turn": "",
      "votingType": "Simbólica"
    }
  ]
}