{
  "@id": "/@@materias/215110",
  "@type": "Materia",
  "accessoryDocument": [],
  "amendment": [],
  "attached": [],
  "authorship": [
    {
      "description": "Parlamentar",
      "firstAuthor": true,
      "title": "Gláucia da Saúde (PL)"
    }
  ],
  "committeeOpinion": [],
  "date": "2025-04-09",
  "description": "Limpeza, capina e roçagem de canteiro central - Avenida Luiz Fernandes Quirino Bairro Jardim Botânico ",
  "file": [
    {
      "content-type": "application/pdf",
      "download": "/@@sapl_documentos_download?path=materia/215110_texto_integral.pdf",
      "filename": "215110_texto_integral.pdf",
      "size": "515.6 KB"
    }
  ],
  "id": "215110",
  "inProgress": false,
  "permissions": {
    "canAddDocument": false,
    "canTramitar": false,
    "showAcompanhar": false,
    "showPastaDigital": true,
    "tramitarModalUrl": ""
  },
  "processing": [
    {
      "date": "2025-04-10 13:41:12",
      "deadline": null,
      "description": "",
      "destinationUnit": "Arquivo",
      "file": [
        {
          "content-type": "application/pdf",
          "download": "/@@sapl_documentos_download?path=materia/tramitacao/590364_tram.pdf",
          "filename": "590364_tram.pdf",
          "size": "21.2 KB"
        }
      ],
      "last": true,
      "sourceUnit": "Seção de Controle de Processo Legislativo",
      "title": "Arquivado"
    },
    {
      "date": "2025-04-10 12:14:25",
      "deadline": null,
      "description": "",
      "destinationUnit": "Seção de Controle de Processo Legislativo",
      "file": [
        {
          "content-type": "application/pdf",
          "download": "/@@sapl_documentos_download?path=materia/tramitacao/590089_tram.pdf",
          "filename": "590089_tram.pdf",
          "size": "21.3 KB"
        }
      ],
      "last": false,
      "sourceUnit": "Plenário",
      "title": "Aprovado"
    },
    {
      "date": "2025-04-09 14:02:04",
      "deadline": null,
      "description": "",
      "destinationUnit": "Plenário",
      "file": [
        {
          "content-type": "application/pdf",
          "download": "/@@sapl_documentos_download?path=materia/tramitacao/589594_tram.pdf",
          "filename": "589594_tram.pdf",
          "size": "21.3 KB"
        }
      ],
      "last": false,
      "sourceUnit": "Departamento Técnico Legislativo",
      "title": "Incluído na Pauta - Requerimento/Indicação/Moção/Pedido Inf"
    },
    {
      "date": "2025-04-09 13:00:34",
      "deadline": null,
      "description": "<p>Proposição eletrônica enviada em 09/04/2025 11:43:32. Matéria incorporada em 09/04/2025 13:00:34 sob protocolo nº 10584/2025</p>",
      "destinationUnit": "Departamento Técnico Legislativo",
      "file": [
        {
          "content-type": "application/pdf",
          "download": "/@@sapl_documentos_download?path=materia/tramitacao/589313_tram.pdf",
          "filename": "589313_tram.pdf",
          "size": "21.4 KB"
        }
      ],
      "last": false,
      "sourceUnit": "Protocolo Eletrônico",
      "title": "Recebimento no Protocolo"
    }
  ],
  "processingRegime": "Ordinário",
  "processingRegime_id": "1",
  "protocol": "10584/2025",
  "quorum": "Maioria simples",
  "quorum_id": "1",
  "remoteUrl": "/consultas/materia/materia_mostrar_proc?cod_materia=215110",
  "substitute": [],
  "title": "Requerimento nº 9786/2025",
  "voteResult": [
    {
      "@id": "/@@sessoes/1531",
      "cod_ordem": 245597,
      "cod_sessao_plen": 1531,
      "date": "2025-04-10",
      "description": "Expediente da 8ª Reunião Ordinária",
      "result": [
        {
          "absent": 0,
          "abstention": 0,
          "contrary": 0,
          "favorable": 0
        }
      ],
      "resultModalUrl": "/consultas/sessao_plenaria/sessao_plenaria_mostrar_painel_proc?cod_sessao_plen=1531&cod_ordem=245597&cod_materia=215110&tipo_materia=expediente&modal=1",
      "title": "Aprovado",
      "turn": "",
      "votingType": "Simbólica"
    }
  ]
}