{
  "@id": "/@@materias/215805",
  "@type": "Materia",
  "accessoryDocument": [],
  "amendment": [],
  "attached": [
    {
      "@id": "/@@materias/204499",
      "@type": "Materia",
      "annexationDate": "2025-04-15",
      "description": "ALTERA A LEI Nº 10.702, DE 10 DE MARÇO DE 2011, QUE \"DISCIPLINA A INSTITUIÇÃO DE FEIRAS LIVRES NO MUNICÍPIO DE UBERLÂNDIA, REVOGA OS DECRETOS Nº 5664 DE 13 DE NOVEMBRO DE 1992; Nº 6757/95; Nº 7870/99; Nº 7961/99; Nº 8356/00; Nº 8569/01; Nº 8461/02 E OS ARTIGOS 24 E 25 DA LEI Nº 4744/88 E DÁ OUTRAS PROVIDÊNCIAS\".",
      "id": "204499",
      "title": "Projeto de Lei Ordinária nº 31/2025"
    }
  ],
  "authorship": [
    {
      "description": "Parlamentar",
      "firstAuthor": true,
      "title": "Liza Prado (CIDADANIA)"
    },
    {
      "description": "Parlamentar",
      "firstAuthor": false,
      "title": "Dr. Igino (PT)"
    },
    {
      "description": "Parlamentar",
      "firstAuthor": false,
      "title": "Ronaldo Tannús (PODEMOS)"
    }
  ],
  "committeeOpinion": [],
  "date": "2025-04-15",
  "description": "com fulcro no caput art.  172 do Regimento interno venho requerer que o Projeto de Lei Ordinária nº 31/2025 - ALTERA A LEI Nº 10.702, DE 10 DE MARÇO DE 2011, QUE \"DISCIPLINA A INSTITUIÇÃO DE FEIRAS LIVRES NO MUNICÍPIO DE UBERLÂNDIA, REVOGA OS DECRETOS Nº 5664 DE 13 DE NOVEMBRO DE 1992; Nº 6757/95; Nº 7870/99; Nº 7961/99; Nº 8356/00; Nº 8569/01; Nº 8461/02 E OS ARTIGOS 24 E 25 DA LEI Nº 4744/88 E DÁ OUTRAS PROVIDÊNCIAS, seja apreciado pelo plenário. ",
  "file": [
    {
      "content-type": "application/pdf",
      "download": "/@@sapl_documentos_download?path=materia/215805_texto_integral.pdf",
      "filename": "215805_texto_integral.pdf",
      "size": "867.2 KB"
    }
  ],
  "id": "215805",
  "inProgress": false,
  "permissions": {
    "canAddDocument": false,
    "canTramitar": false,
    "showAcompanhar": false,
    "showPastaDigital": true,
    "tramitarModalUrl": ""
  },
  "processing": [
    {
      "date": "2025-05-05 12:32:18",
      "deadline": null,
      "description": "",
      "destinationUnit": "Arquivo",
      "file": [
        {
          "content-type": "application/pdf",
          "download": "/@@sapl_documentos_download?path=materia/tramitacao/601669_tram.pdf",
          "filename": "601669_tram.pdf",
          "size": "21.6 KB"
        }
      ],
      "last": true,
      "sourceUnit": "Seção de Controle de Processo Legislativo",
      "title": "Arquivado"
    },
    {
      "date": "2025-05-05 10:52:30",
      "deadline": null,
      "description": "",
      "destinationUnit": "Seção de Controle de Processo Legislativo",
      "file": [
        {
          "content-type": "application/pdf",
          "download": "/@@sapl_documentos_download?path=materia/tramitacao/596139_tram.pdf",
          "filename": "596139_tram.pdf",
          "size": "21.6 KB"
        }
      ],
      "last": false,
      "sourceUnit": "Plenário",
      "title": "Aprovado"
    },
    {
      "date": "2025-04-28 12:51:10",
      "deadline": null,
      "description": "",
      "destinationUnit": "Plenário",
      "file": [
        {
          "content-type": "application/pdf",
          "download": "/@@sapl_documentos_download?path=materia/tramitacao/593757_tram.pdf",
          "filename": "593757_tram.pdf",
          "size": "21.7 KB"
        }
      ],
      "last": false,
      "sourceUnit": "Departamento Técnico Legislativo",
      "title": "Incluído na Pauta - Requerimento/Indicação/Moção/Pedido Inf"
    },
    {
      "date": "2025-04-15 09:54:19",
      "deadline": null,
      "description": "<p>Proposição eletrônica enviada em 14/04/2025 11:07:39. Matéria incorporada em 15/04/2025 09:54:19 sob protocolo nº 11265/2025</p>",
      "destinationUnit": "Departamento Técnico Legislativo",
      "file": [
        {
          "content-type": "application/pdf",
          "download": "/@@sapl_documentos_download?path=materia/tramitacao/592577_tram.pdf",
          "filename": "592577_tram.pdf",
          "size": "21.8 KB"
        }
      ],
      "last": false,
      "sourceUnit": "Protocolo Eletrônico",
      "title": "Recebimento no Protocolo"
    }
  ],
  "processingRegime": "Ordinário",
  "processingRegime_id": "1",
  "protocol": "11265/2025",
  "quorum": "Maioria simples",
  "quorum_id": "1",
  "remoteUrl": "/consultas/materia/materia_mostrar_proc?cod_materia=215805",
  "substitute": [],
  "title": "Requerimento nº 10427/2025",
  "voteResult": [
    {
      "@id": "/@@sessoes/1536",
      "cod_ordem": 246608,
      "cod_sessao_plen": 1536,
      "date": "2025-05-05",
      "description": "Expediente da 1ª Reunião Ordinária",
      "result": [
        {
          "absent": 0,
          "abstention": 0,
          "contrary": 0,
          "favorable": 0
        }
      ],
      "resultModalUrl": "/consultas/sessao_plenaria/sessao_plenaria_mostrar_painel_proc?cod_sessao_plen=1536&cod_ordem=246608&cod_materia=215805&tipo_materia=expediente&modal=1",
      "title": "Aprovado",
      "turn": "",
      "votingType": "Simbólica"
    }
  ]
}