{
  "@id": "/@@materias/215897",
  "@type": "Materia",
  "accessoryDocument": [],
  "amendment": [],
  "attached": [],
  "authorship": [
    {
      "description": "Parlamentar",
      "firstAuthor": true,
      "title": "Edinho Combate Ao Câncer (DEMOCRATA)"
    }
  ],
  "committeeOpinion": [],
  "date": "2025-04-15",
  "description": "Requer-se a realização de retirada de lixo e limpeza do lote abandonado  no endereço - R. Tapuios, 1286 - Saraiva, 38408-416.\r\n",
  "file": [
    {
      "content-type": "application/pdf",
      "download": "/@@sapl_documentos_download?path=materia/215897_texto_integral.pdf",
      "filename": "215897_texto_integral.pdf",
      "size": "758.6 KB"
    }
  ],
  "id": "215897",
  "inProgress": false,
  "permissions": {
    "canAddDocument": false,
    "canTramitar": false,
    "showAcompanhar": false,
    "showPastaDigital": true,
    "tramitarModalUrl": ""
  },
  "processing": [
    {
      "date": "2025-05-05 14:20:21",
      "deadline": null,
      "description": "",
      "destinationUnit": "Arquivo",
      "file": [
        {
          "content-type": "application/pdf",
          "download": "/@@sapl_documentos_download?path=materia/tramitacao/604207_tram.pdf",
          "filename": "604207_tram.pdf",
          "size": "21.3 KB"
        }
      ],
      "last": true,
      "sourceUnit": "Seção de Controle de Processo Legislativo",
      "title": "Arquivado"
    },
    {
      "date": "2025-05-05 14:18:20",
      "deadline": null,
      "description": "",
      "destinationUnit": "Arquivo",
      "file": [
        {
          "content-type": "application/pdf",
          "download": "/@@sapl_documentos_download?path=materia/tramitacao/602225_tram.pdf",
          "filename": "602225_tram.pdf",
          "size": "21.3 KB"
        }
      ],
      "last": false,
      "sourceUnit": "Seção de Controle de Processo Legislativo",
      "title": "Arquivado"
    },
    {
      "date": "2025-05-05 10:55:37",
      "deadline": null,
      "description": "",
      "destinationUnit": "Seção de Controle de Processo Legislativo",
      "file": [
        {
          "content-type": "application/pdf",
          "download": "/@@sapl_documentos_download?path=materia/tramitacao/596229_tram.pdf",
          "filename": "596229_tram.pdf",
          "size": "21.3 KB"
        }
      ],
      "last": false,
      "sourceUnit": "Plenário",
      "title": "Aprovado"
    },
    {
      "date": "2025-04-28 12:51:10",
      "deadline": null,
      "description": "",
      "destinationUnit": "Plenário",
      "file": [
        {
          "content-type": "application/pdf",
          "download": "/@@sapl_documentos_download?path=materia/tramitacao/593847_tram.pdf",
          "filename": "593847_tram.pdf",
          "size": "21.3 KB"
        }
      ],
      "last": false,
      "sourceUnit": "Departamento Técnico Legislativo",
      "title": "Incluído na Pauta - Requerimento/Indicação/Moção/Pedido Inf"
    },
    {
      "date": "2025-04-15 11:26:08",
      "deadline": null,
      "description": "<p>Proposição eletrônica enviada em 15/04/2025 10:04:57. Matéria incorporada em 15/04/2025 11:26:08 sob protocolo nº 11358/2025</p>",
      "destinationUnit": "Departamento Técnico Legislativo",
      "file": [
        {
          "content-type": "application/pdf",
          "download": "/@@sapl_documentos_download?path=materia/tramitacao/592670_tram.pdf",
          "filename": "592670_tram.pdf",
          "size": "21.4 KB"
        }
      ],
      "last": false,
      "sourceUnit": "Protocolo Eletrônico",
      "title": "Recebimento no Protocolo"
    }
  ],
  "processingRegime": "Ordinário",
  "processingRegime_id": "1",
  "protocol": "11358/2025",
  "quorum": "Maioria simples",
  "quorum_id": "1",
  "remoteUrl": "/consultas/materia/materia_mostrar_proc?cod_materia=215897",
  "substitute": [],
  "title": "Requerimento nº 10517/2025",
  "voteResult": [
    {
      "@id": "/@@sessoes/1536",
      "cod_ordem": 246698,
      "cod_sessao_plen": 1536,
      "date": "2025-05-05",
      "description": "Expediente da 1ª Reunião Ordinária",
      "result": [
        {
          "absent": 0,
          "abstention": 0,
          "contrary": 0,
          "favorable": 0
        }
      ],
      "resultModalUrl": "/consultas/sessao_plenaria/sessao_plenaria_mostrar_painel_proc?cod_sessao_plen=1536&cod_ordem=246698&cod_materia=215897&tipo_materia=expediente&modal=1",
      "title": "Aprovado",
      "turn": "",
      "votingType": "Simbólica"
    }
  ]
}