{
  "@id": "/@@materias/223811",
  "@type": "Materia",
  "accessoryDocument": [],
  "amendment": [],
  "attached": [],
  "authorship": [
    {
      "description": "Parlamentar",
      "firstAuthor": true,
      "title": "Anderson Lima (PL)"
    }
  ],
  "committeeOpinion": [],
  "date": "2025-06-25",
  "description": "Operação tapa-buraco na R. das Borboletas esquina com a R. Mangaba - Morumbi, 38407-174",
  "file": [
    {
      "content-type": "application/pdf",
      "download": "/@@sapl_documentos_download?path=materia/223811_texto_integral.pdf",
      "filename": "223811_texto_integral.pdf",
      "size": "126.7 KB"
    }
  ],
  "id": "223811",
  "inProgress": false,
  "permissions": {
    "canAddDocument": false,
    "canTramitar": false,
    "showAcompanhar": false,
    "showPastaDigital": true,
    "tramitarModalUrl": ""
  },
  "processing": [
    {
      "date": "2025-07-01 15:57:57",
      "deadline": null,
      "description": "",
      "destinationUnit": "Arquivo",
      "file": [
        {
          "content-type": "application/pdf",
          "download": "/@@sapl_documentos_download?path=materia/tramitacao/638581_tram.pdf",
          "filename": "638581_tram.pdf",
          "size": "21.2 KB"
        }
      ],
      "last": true,
      "sourceUnit": "Seção de Controle de Processo Legislativo",
      "title": "Arquivado"
    },
    {
      "date": "2025-07-01 12:29:19",
      "deadline": null,
      "description": "",
      "destinationUnit": "Seção de Controle de Processo Legislativo",
      "file": [
        {
          "content-type": "application/pdf",
          "download": "/@@sapl_documentos_download?path=materia/tramitacao/636932_tram.pdf",
          "filename": "636932_tram.pdf",
          "size": "21.2 KB"
        }
      ],
      "last": false,
      "sourceUnit": "Plenário",
      "title": "Aprovado"
    },
    {
      "date": "2025-07-01 12:27:03",
      "deadline": null,
      "description": "",
      "destinationUnit": "Seção de Controle de Processo Legislativo",
      "file": [
        {
          "content-type": "application/pdf",
          "download": "/@@sapl_documentos_download?path=materia/tramitacao/634938_tram.pdf",
          "filename": "634938_tram.pdf",
          "size": "21.2 KB"
        }
      ],
      "last": false,
      "sourceUnit": "Plenário",
      "title": "Aprovado"
    },
    {
      "date": "2025-06-26 10:35:34",
      "deadline": null,
      "description": "",
      "destinationUnit": "Plenário",
      "file": [
        {
          "content-type": "application/pdf",
          "download": "/@@sapl_documentos_download?path=materia/tramitacao/633075_tram.pdf",
          "filename": "633075_tram.pdf",
          "size": "21.3 KB"
        }
      ],
      "last": false,
      "sourceUnit": "Departamento Técnico Legislativo",
      "title": "Incluído na Pauta - Requerimento/Indicação/Moção/Pedido Inf"
    },
    {
      "date": "2025-06-25 14:42:28",
      "deadline": null,
      "description": "<p>Proposição eletrônica enviada em 25/06/2025 14:17:01. Matéria incorporada em 25/06/2025 14:42:28 sob protocolo nº 19198/2025</p>",
      "destinationUnit": "Departamento Técnico Legislativo",
      "file": [
        {
          "content-type": "application/pdf",
          "download": "/@@sapl_documentos_download?path=materia/tramitacao/632776_tram.pdf",
          "filename": "632776_tram.pdf",
          "size": "21.4 KB"
        }
      ],
      "last": false,
      "sourceUnit": "Protocolo Eletrônico",
      "title": "Recebimento no Protocolo"
    }
  ],
  "processingRegime": "Ordinário",
  "processingRegime_id": "1",
  "protocol": "19198/2025",
  "quorum": "Maioria simples",
  "quorum_id": "1",
  "remoteUrl": "/consultas/materia/materia_mostrar_proc?cod_materia=223811",
  "substitute": [],
  "title": "Requerimento nº 17936/2025",
  "voteResult": [
    {
      "@id": "/@@sessoes/1560",
      "cod_ordem": 255475,
      "cod_sessao_plen": 1560,
      "date": "2025-07-01",
      "description": "Expediente da 1ª Reunião Ordinária",
      "result": [
        {
          "absent": 0,
          "abstention": 0,
          "contrary": 0,
          "favorable": 0
        }
      ],
      "resultModalUrl": "/consultas/sessao_plenaria/sessao_plenaria_mostrar_painel_proc?cod_sessao_plen=1560&cod_ordem=255475&cod_materia=223811&tipo_materia=expediente&modal=1",
      "title": "Aprovado",
      "turn": "",
      "votingType": "Simbólica"
    }
  ]
}