{
  "@id": "/@@sessoes/id/1539/votacao",
  "@type": "votacaoNominal",
  "description": "4ª Reunião Ordinária – 08/05/2025",
  "items": [
    {
      "@id": "/@@materias/204499",
      "@type": "Materia",
      "abstencao": 0,
      "apuracao": [
        {
          "resultado": "Mantido Parecer Contrário CLJR"
        }
      ],
      "ausente": 8,
      "autoria": [
        {
          "description": "Parlamentar",
          "id": "399022",
          "primeiro_autor": true,
          "title": "Liza Prado"
        }
      ],
      "contrario": 5,
      "description": "ALTERA A LEI Nº 10.702, DE 10 DE MARÇO DE 2011, QUE \"DISCIPLINA A INSTITUIÇÃO DE FEIRAS LIVRES NO MUNICÍPIO DE UBERLÂNDIA, REVOGA OS DECRETOS Nº 5664 DE 13 DE NOVEMBRO DE 1992; Nº 6757/95; Nº 7870/99; Nº 7961/99; Nº 8356/00; Nº 8569/01; Nº 8461/02 E OS ARTIGOS 24 E 25 DA LEI Nº 4744/88 E DÁ OUTRAS PROVIDÊNCIAS\".",
      "favoravel": 13,
      "id": "204499",
      "presidencia": 1,
      "quorum": "Maioria qualificada - 2/3",
      "tipo_votacao": "Nominal",
      "title": "Projeto de Lei Ordinária nº 31/2025",
      "turno": "Apreciar parecer contrário",
      "votos": [
        {
          "abstencao": [],
          "ausente": [
            {
              "@id": "/@@vereadores/25988",
              "@type": "Vereador",
              "description": "Adriano Zago",
              "id": "25988",
              "partido": [
                {
                  "title": "AVANTE",
                  "token": "AVANTE"
                }
              ],
              "title": "Adriano Zago",
              "votacao_id": "38173",
              "voto": "Ausente"
            },
            {
              "@id": "/@@vereadores/528006",
              "@type": "Vereador",
              "description": "Ronaldo César Vilela Tannús",
              "id": "528006",
              "partido": [
                {
                  "title": "PODEMOS",
                  "token": "PODEMOS"
                }
              ],
              "title": "Ronaldo Tannús",
              "votacao_id": "38173",
              "voto": "Ausente"
            },
            {
              "@id": "/@@vereadores/537380",
              "@type": "Vereador",
              "description": "Antônio Augusto Gonçalves Goulart",
              "id": "537380",
              "partido": [
                {
                  "title": "PARTIDO DA SOCIAL DEMOCRACIA BRASILEIRA",
                  "token": "PSDB"
                }
              ],
              "title": "Antônio Augusto Queijinho",
              "votacao_id": "38173",
              "voto": "Ausente"
            },
            {
              "@id": "/@@vereadores/537427",
              "@type": "Vereador",
              "description": "Anderson Lima",
              "id": "537427",
              "partido": [
                {
                  "title": "PARTIDO LIBERAL",
                  "token": "PL"
                }
              ],
              "title": "Anderson Lima",
              "votacao_id": "38173",
              "voto": "Ausente"
            },
            {
              "@id": "/@@vereadores/543274",
              "@type": "Vereador",
              "description": "Sérvio Túlio",
              "id": "543274",
              "partido": [
                {
                  "title": "PARTIDO DA SOCIAL DEMOCRACIA BRASILEIRA",
                  "token": "PSDB"
                }
              ],
              "title": "Sérvio Túlio",
              "votacao_id": "38173",
              "voto": "Ausente"
            },
            {
              "@id": "/@@vereadores/546914",
              "@type": "Vereador",
              "description": "Abatenio de Andrade Marquez Neto",
              "id": "546914",
              "partido": [
                {
                  "title": "PROGRESSISTAS",
                  "token": "PP"
                }
              ],
              "title": "Abatenio Marquez",
              "votacao_id": "38173",
              "voto": "Ausente"
            },
            {
              "@id": "/@@vereadores/556178",
              "@type": "Vereador",
              "description": "Edson Carvalho Ferreira",
              "id": "556178",
              "partido": [
                {
                  "title": "Democrata",
                  "token": "DEMOCRATA"
                }
              ],
              "title": "Edinho Combate Ao Câncer",
              "votacao_id": "38173",
              "voto": "Ausente"
            },
            {
              "@id": "/@@vereadores/556183",
              "@type": "Vereador",
              "description": "Conrado Augusto Ferreira de Oliveira",
              "id": "556183",
              "partido": [
                {
                  "title": "MOVIMENTO DEMOCRÁTICO BRASILEIRO",
                  "token": "MDB"
                }
              ],
              "title": "Prof. Conrado Augusto",
              "votacao_id": "38173",
              "voto": "Ausente"
            }
          ],
          "contrario": [
            {
              "@id": "/@@vereadores/399022",
              "@type": "Vereador",
              "description": "Liza Fernandes Prado",
              "id": "399022",
              "partido": [
                {
                  "title": "CIDADANIA",
                  "token": "CIDADANIA"
                }
              ],
              "title": "Liza Prado",
              "votacao_id": "38173",
              "voto": "Não"
            },
            {
              "@id": "/@@vereadores/537428",
              "@type": "Vereador",
              "description": "Amanda Gondim",
              "id": "537428",
              "partido": [
                {
                  "title": "PARTIDO SOCIALISTA BRASILEIRO",
                  "token": "PSB"
                }
              ],
              "title": "Amanda Gondim",
              "votacao_id": "38173",
              "voto": "Não"
            },
            {
              "@id": "/@@vereadores/537431",
              "@type": "Vereador",
              "description": "Fabio Dias Queiroz Zavitoski",
              "id": "537431",
              "partido": [
                {
                  "title": "PARTIDO VERDE",
                  "token": "PV"
                }
              ],
              "title": "Fabão",
              "votacao_id": "38173",
              "voto": "Não"
            },
            {
              "@id": "/@@vereadores/552091",
              "@type": "Vereador",
              "description": "Igino Marcos da Mata de Oliveira",
              "id": "552091",
              "partido": [
                {
                  "title": "PARTIDO DOS TRABALHADORES",
                  "token": "PT"
                }
              ],
              "title": "Dr. Igino",
              "votacao_id": "38173",
              "voto": "Não"
            },
            {
              "@id": "/@@vereadores/556184",
              "@type": "Vereador",
              "description": "Ronaldo Amélio Ferreira",
              "id": "556184",
              "partido": [
                {
                  "title": "PARTIDO DOS TRABALHADORES",
                  "token": "PT"
                }
              ],
              "title": "Prof. Ronaldo",
              "votacao_id": "38173",
              "voto": "Não"
            }
          ],
          "favoravel": [
            {
              "@id": "/@@vereadores/26010",
              "@type": "Vereador",
              "description": "Gláucia Galante Buíssa",
              "id": "26010",
              "partido": [
                {
                  "title": "PARTIDO LIBERAL",
                  "token": "PL"
                }
              ],
              "title": "Gláucia da Saúde",
              "votacao_id": "38173",
              "voto": "Sim"
            },
            {
              "@id": "/@@vereadores/399041",
              "@type": "Vereador",
              "description": "Antônio Carrijo",
              "id": "399041",
              "partido": [
                {
                  "title": "PROGRESSISTAS",
                  "token": "PP"
                }
              ],
              "title": "Antônio Carrijo",
              "votacao_id": "38173",
              "voto": "Sim"
            },
            {
              "@id": "/@@vereadores/526697",
              "@type": "Vereador",
              "description": "Ednaldo Régio de Lima",
              "id": "526697",
              "partido": [
                {
                  "title": "PROGRESSISTAS",
                  "token": "PP"
                }
              ],
              "title": "Sargento Ednaldo",
              "votacao_id": "38173",
              "voto": "Sim"
            },
            {
              "@id": "/@@vereadores/537433",
              "@type": "Vereador",
              "description": "Ivan da Silva Nunes",
              "id": "537433",
              "partido": [
                {
                  "title": "PROGRESSISTAS",
                  "token": "PP"
                }
              ],
              "title": "Ivan Nunes",
              "votacao_id": "38173",
              "voto": "Sim"
            },
            {
              "@id": "/@@vereadores/537434",
              "@type": "Vereador",
              "description": "Neemias Miquéias",
              "id": "537434",
              "partido": [
                {
                  "title": "PODEMOS",
                  "token": "PODEMOS"
                }
              ],
              "title": "Neemias Miquéias",
              "votacao_id": "38173",
              "voto": "Sim"
            },
            {
              "@id": "/@@vereadores/537436",
              "@type": "Vereador",
              "description": "Thais Andrade",
              "id": "537436",
              "partido": [
                {
                  "title": "Unão Brasil",
                  "token": "União Brasil"
                }
              ],
              "title": "Thais Andrade",
              "votacao_id": "38173",
              "voto": "Sim"
            },
            {
              "@id": "/@@vereadores/556174",
              "@type": "Vereador",
              "description": "Jair Ferraz",
              "id": "556174",
              "partido": [
                {
                  "title": "PROGRESSISTAS",
                  "token": "PP"
                }
              ],
              "title": "Jair Ferraz",
              "votacao_id": "38173",
              "voto": "Sim"
            },
            {
              "@id": "/@@vereadores/556176",
              "@type": "Vereador",
              "description": "Ângela Aparecida Caetano Souza",
              "id": "556176",
              "partido": [
                {
                  "title": "Solidariedade",
                  "token": "Solidariedade"
                }
              ],
              "title": "Ângela Do Postinho",
              "votacao_id": "38173",
              "voto": "Sim"
            },
            {
              "@id": "/@@vereadores/556177",
              "@type": "Vereador",
              "description": "Lia Eunice Valechi da Silva",
              "id": "556177",
              "partido": [
                {
                  "title": "Unão Brasil",
                  "token": "União Brasil"
                }
              ],
              "title": "Delegada Lia Valechi",
              "votacao_id": "38173",
              "voto": "Sim"
            },
            {
              "@id": "/@@vereadores/556179",
              "@type": "Vereador",
              "description": "Eliusmarcio Alves de Carvalho (Elinho da Academia)",
              "id": "556179",
              "partido": [
                {
                  "title": "PARTIDO DA MOBILIZAÇÃO NACIONAL",
                  "token": "MOBILIZA"
                }
              ],
              "title": "Elinho Da Academia",
              "votacao_id": "38173",
              "voto": "Sim"
            },
            {
              "@id": "/@@vereadores/556180",
              "@type": "Vereador",
              "description": "Janaina Guimarães Parreira Rezende",
              "id": "556180",
              "partido": [
                {
                  "title": "PARTIDO LIBERAL",
                  "token": "PL"
                }
              ],
              "title": "Janaina Guimarães",
              "votacao_id": "38173",
              "voto": "Sim"
            },
            {
              "@id": "/@@vereadores/556181",
              "@type": "Vereador",
              "description": "Nei Carlos Borges",
              "id": "556181",
              "partido": [
                {
                  "title": "Solidariedade",
                  "token": "Solidariedade"
                }
              ],
              "title": "Nei Borges",
              "votacao_id": "38173",
              "voto": "Sim"
            },
            {
              "@id": "/@@vereadores/556182",
              "@type": "Vereador",
              "description": "Celisvaldo da Silva ",
              "id": "556182",
              "partido": [
                {
                  "title": "DEMOCRACIA CRISTÃ",
                  "token": "DC"
                }
              ],
              "title": "Pezão Do Esporte",
              "votacao_id": "38173",
              "voto": "Sim"
            }
          ],
          "presidencia": [
            {
              "@id": "/@@vereadores/26097",
              "@type": "Vereador",
              "description": "Rosenvaldo Correia de Mendonça",
              "id": "26097",
              "partido": [
                {
                  "title": "PROGRESSISTAS",
                  "token": "PP"
                }
              ],
              "title": "Zezinho Mendonça",
              "votacao_id": "38173",
              "voto": "Na Presidência"
            }
          ]
        }
      ]
    },
    {
      "@id": "/@@materias/204500",
      "@type": "Materia",
      "abstencao": 0,
      "apuracao": [
        {
          "resultado": "Mantido Parecer Contrário CLJR"
        }
      ],
      "ausente": 9,
      "autoria": [
        {
          "description": "Parlamentar",
          "id": "399022",
          "primeiro_autor": true,
          "title": "Liza Prado"
        }
      ],
      "contrario": 7,
      "description": "ALTERA A LEI Nº 13.619, DE 5 DE NOVEMBRO DE 2021 QUE DISPÕE SOBRE O DIREITO DE PREFERÊNCIA NA MATRÍCULA E NA TRANSFERÊNCIA DOS DEPENDENTES DA MULHER VÍTIMA DE VIOLÊNCIA DOMÉSTICA E FAMILIAR E DA MULHER MÃE SOLO EM INSTITUIÇÃO DE EDUCAÇÃO BÁSICA MAIS PRÓXIMA DE SEU DOMICÍLIO.",
      "favoravel": 10,
      "id": "204500",
      "presidencia": 1,
      "quorum": "Maioria qualificada - 2/3",
      "tipo_votacao": "Nominal",
      "title": "Projeto de Lei Ordinária nº 32/2025",
      "turno": "Apreciar parecer contrário",
      "votos": [
        {
          "abstencao": [],
          "ausente": [
            {
              "@id": "/@@vereadores/526697",
              "@type": "Vereador",
              "description": "Ednaldo Régio de Lima",
              "id": "526697",
              "partido": [
                {
                  "title": "PROGRESSISTAS",
                  "token": "PP"
                }
              ],
              "title": "Sargento Ednaldo",
              "votacao_id": "38174",
              "voto": "Ausente"
            },
            {
              "@id": "/@@vereadores/528006",
              "@type": "Vereador",
              "description": "Ronaldo César Vilela Tannús",
              "id": "528006",
              "partido": [
                {
                  "title": "PODEMOS",
                  "token": "PODEMOS"
                }
              ],
              "title": "Ronaldo Tannús",
              "votacao_id": "38174",
              "voto": "Ausente"
            },
            {
              "@id": "/@@vereadores/537380",
              "@type": "Vereador",
              "description": "Antônio Augusto Gonçalves Goulart",
              "id": "537380",
              "partido": [
                {
                  "title": "PARTIDO DA SOCIAL DEMOCRACIA BRASILEIRA",
                  "token": "PSDB"
                }
              ],
              "title": "Antônio Augusto Queijinho",
              "votacao_id": "38174",
              "voto": "Ausente"
            },
            {
              "@id": "/@@vereadores/537427",
              "@type": "Vereador",
              "description": "Anderson Lima",
              "id": "537427",
              "partido": [
                {
                  "title": "PARTIDO LIBERAL",
                  "token": "PL"
                }
              ],
              "title": "Anderson Lima",
              "votacao_id": "38174",
              "voto": "Ausente"
            },
            {
              "@id": "/@@vereadores/543274",
              "@type": "Vereador",
              "description": "Sérvio Túlio",
              "id": "543274",
              "partido": [
                {
                  "title": "PARTIDO DA SOCIAL DEMOCRACIA BRASILEIRA",
                  "token": "PSDB"
                }
              ],
              "title": "Sérvio Túlio",
              "votacao_id": "38174",
              "voto": "Ausente"
            },
            {
              "@id": "/@@vereadores/546914",
              "@type": "Vereador",
              "description": "Abatenio de Andrade Marquez Neto",
              "id": "546914",
              "partido": [
                {
                  "title": "PROGRESSISTAS",
                  "token": "PP"
                }
              ],
              "title": "Abatenio Marquez",
              "votacao_id": "38174",
              "voto": "Ausente"
            },
            {
              "@id": "/@@vereadores/556174",
              "@type": "Vereador",
              "description": "Jair Ferraz",
              "id": "556174",
              "partido": [
                {
                  "title": "PROGRESSISTAS",
                  "token": "PP"
                }
              ],
              "title": "Jair Ferraz",
              "votacao_id": "38174",
              "voto": "Ausente"
            },
            {
              "@id": "/@@vereadores/556179",
              "@type": "Vereador",
              "description": "Eliusmarcio Alves de Carvalho (Elinho da Academia)",
              "id": "556179",
              "partido": [
                {
                  "title": "PARTIDO DA MOBILIZAÇÃO NACIONAL",
                  "token": "MOBILIZA"
                }
              ],
              "title": "Elinho Da Academia",
              "votacao_id": "38174",
              "voto": "Ausente"
            },
            {
              "@id": "/@@vereadores/556182",
              "@type": "Vereador",
              "description": "Celisvaldo da Silva ",
              "id": "556182",
              "partido": [
                {
                  "title": "DEMOCRACIA CRISTÃ",
                  "token": "DC"
                }
              ],
              "title": "Pezão Do Esporte",
              "votacao_id": "38174",
              "voto": "Ausente"
            }
          ],
          "contrario": [
            {
              "@id": "/@@vereadores/25988",
              "@type": "Vereador",
              "description": "Adriano Zago",
              "id": "25988",
              "partido": [
                {
                  "title": "AVANTE",
                  "token": "AVANTE"
                }
              ],
              "title": "Adriano Zago",
              "votacao_id": "38174",
              "voto": "Não"
            },
            {
              "@id": "/@@vereadores/399022",
              "@type": "Vereador",
              "description": "Liza Fernandes Prado",
              "id": "399022",
              "partido": [
                {
                  "title": "CIDADANIA",
                  "token": "CIDADANIA"
                }
              ],
              "title": "Liza Prado",
              "votacao_id": "38174",
              "voto": "Não"
            },
            {
              "@id": "/@@vereadores/537428",
              "@type": "Vereador",
              "description": "Amanda Gondim",
              "id": "537428",
              "partido": [
                {
                  "title": "PARTIDO SOCIALISTA BRASILEIRO",
                  "token": "PSB"
                }
              ],
              "title": "Amanda Gondim",
              "votacao_id": "38174",
              "voto": "Não"
            },
            {
              "@id": "/@@vereadores/537431",
              "@type": "Vereador",
              "description": "Fabio Dias Queiroz Zavitoski",
              "id": "537431",
              "partido": [
                {
                  "title": "PARTIDO VERDE",
                  "token": "PV"
                }
              ],
              "title": "Fabão",
              "votacao_id": "38174",
              "voto": "Não"
            },
            {
              "@id": "/@@vereadores/552091",
              "@type": "Vereador",
              "description": "Igino Marcos da Mata de Oliveira",
              "id": "552091",
              "partido": [
                {
                  "title": "PARTIDO DOS TRABALHADORES",
                  "token": "PT"
                }
              ],
              "title": "Dr. Igino",
              "votacao_id": "38174",
              "voto": "Não"
            },
            {
              "@id": "/@@vereadores/556183",
              "@type": "Vereador",
              "description": "Conrado Augusto Ferreira de Oliveira",
              "id": "556183",
              "partido": [
                {
                  "title": "MOVIMENTO DEMOCRÁTICO BRASILEIRO",
                  "token": "MDB"
                }
              ],
              "title": "Prof. Conrado Augusto",
              "votacao_id": "38174",
              "voto": "Não"
            },
            {
              "@id": "/@@vereadores/556184",
              "@type": "Vereador",
              "description": "Ronaldo Amélio Ferreira",
              "id": "556184",
              "partido": [
                {
                  "title": "PARTIDO DOS TRABALHADORES",
                  "token": "PT"
                }
              ],
              "title": "Prof. Ronaldo",
              "votacao_id": "38174",
              "voto": "Não"
            }
          ],
          "favoravel": [
            {
              "@id": "/@@vereadores/26010",
              "@type": "Vereador",
              "description": "Gláucia Galante Buíssa",
              "id": "26010",
              "partido": [
                {
                  "title": "PARTIDO LIBERAL",
                  "token": "PL"
                }
              ],
              "title": "Gláucia da Saúde",
              "votacao_id": "38174",
              "voto": "Sim"
            },
            {
              "@id": "/@@vereadores/399041",
              "@type": "Vereador",
              "description": "Antônio Carrijo",
              "id": "399041",
              "partido": [
                {
                  "title": "PROGRESSISTAS",
                  "token": "PP"
                }
              ],
              "title": "Antônio Carrijo",
              "votacao_id": "38174",
              "voto": "Sim"
            },
            {
              "@id": "/@@vereadores/537433",
              "@type": "Vereador",
              "description": "Ivan da Silva Nunes",
              "id": "537433",
              "partido": [
                {
                  "title": "PROGRESSISTAS",
                  "token": "PP"
                }
              ],
              "title": "Ivan Nunes",
              "votacao_id": "38174",
              "voto": "Sim"
            },
            {
              "@id": "/@@vereadores/537434",
              "@type": "Vereador",
              "description": "Neemias Miquéias",
              "id": "537434",
              "partido": [
                {
                  "title": "PODEMOS",
                  "token": "PODEMOS"
                }
              ],
              "title": "Neemias Miquéias",
              "votacao_id": "38174",
              "voto": "Sim"
            },
            {
              "@id": "/@@vereadores/537436",
              "@type": "Vereador",
              "description": "Thais Andrade",
              "id": "537436",
              "partido": [
                {
                  "title": "Unão Brasil",
                  "token": "União Brasil"
                }
              ],
              "title": "Thais Andrade",
              "votacao_id": "38174",
              "voto": "Sim"
            },
            {
              "@id": "/@@vereadores/556176",
              "@type": "Vereador",
              "description": "Ângela Aparecida Caetano Souza",
              "id": "556176",
              "partido": [
                {
                  "title": "Solidariedade",
                  "token": "Solidariedade"
                }
              ],
              "title": "Ângela Do Postinho",
              "votacao_id": "38174",
              "voto": "Sim"
            },
            {
              "@id": "/@@vereadores/556177",
              "@type": "Vereador",
              "description": "Lia Eunice Valechi da Silva",
              "id": "556177",
              "partido": [
                {
                  "title": "Unão Brasil",
                  "token": "União Brasil"
                }
              ],
              "title": "Delegada Lia Valechi",
              "votacao_id": "38174",
              "voto": "Sim"
            },
            {
              "@id": "/@@vereadores/556178",
              "@type": "Vereador",
              "description": "Edson Carvalho Ferreira",
              "id": "556178",
              "partido": [
                {
                  "title": "Democrata",
                  "token": "DEMOCRATA"
                }
              ],
              "title": "Edinho Combate Ao Câncer",
              "votacao_id": "38174",
              "voto": "Sim"
            },
            {
              "@id": "/@@vereadores/556180",
              "@type": "Vereador",
              "description": "Janaina Guimarães Parreira Rezende",
              "id": "556180",
              "partido": [
                {
                  "title": "PARTIDO LIBERAL",
                  "token": "PL"
                }
              ],
              "title": "Janaina Guimarães",
              "votacao_id": "38174",
              "voto": "Sim"
            },
            {
              "@id": "/@@vereadores/556181",
              "@type": "Vereador",
              "description": "Nei Carlos Borges",
              "id": "556181",
              "partido": [
                {
                  "title": "Solidariedade",
                  "token": "Solidariedade"
                }
              ],
              "title": "Nei Borges",
              "votacao_id": "38174",
              "voto": "Sim"
            }
          ],
          "presidencia": [
            {
              "@id": "/@@vereadores/26097",
              "@type": "Vereador",
              "description": "Rosenvaldo Correia de Mendonça",
              "id": "26097",
              "partido": [
                {
                  "title": "PROGRESSISTAS",
                  "token": "PP"
                }
              ],
              "title": "Zezinho Mendonça",
              "votacao_id": "38174",
              "voto": "Na Presidência"
            }
          ]
        }
      ]
    },
    {
      "@id": "/@@materias/204501",
      "@type": "Materia",
      "abstencao": 0,
      "apuracao": [],
      "ausente": 0,
      "autoria": [
        {
          "description": "Parlamentar",
          "id": "399022",
          "primeiro_autor": true,
          "title": "Liza Prado"
        }
      ],
      "contrario": 0,
      "description": "ESTABELECE NORMAS DE ATENDIMENTO MÉDICO EM EVENTOS PÚBLICOS OU PRIVADOS COM AGLOMERAÇÃO DE PESSOAS NO MESMO AMBIENTE",
      "favoravel": 0,
      "id": "204501",
      "presidencia": 0,
      "quorum": "Maioria qualificada - 2/3",
      "tipo_votacao": "Nominal",
      "title": "Projeto de Lei Ordinária nº 33/2025",
      "turno": "Apreciar parecer contrário",
      "votos": [
        {
          "abstencao": [],
          "ausente": [],
          "contrario": [],
          "favoravel": [],
          "presidencia": []
        }
      ]
    },
    {
      "@id": "/@@materias/204502",
      "@type": "Materia",
      "abstencao": 0,
      "apuracao": [],
      "ausente": 0,
      "autoria": [
        {
          "description": "Parlamentar",
          "id": "399022",
          "primeiro_autor": true,
          "title": "Liza Prado"
        }
      ],
      "contrario": 0,
      "description": "ESTABELECE A RESERVA DE ASSENTOS PREFERENCIAIS PARA IDOSOS, GESTANTES, OBESOS, LACTANTES E PESSOAS COM DEFICIÊNCIA OU MOBILIDADE REDUZIDA EM TERMINAIS DE INTEGRAÇÃO, ESTAÇÃO FECHADA, ESTAÇÃO DE TRANSFERÊNCIA E PONTOS DE PARADA DE ÔNIBUS NO MUNICÍPIO DE UBERLÂNDIA. ",
      "favoravel": 0,
      "id": "204502",
      "presidencia": 0,
      "quorum": "Maioria qualificada - 2/3",
      "tipo_votacao": "Nominal",
      "title": "Projeto de Lei Ordinária nº 34/2025",
      "turno": "Apreciar parecer contrário",
      "votos": [
        {
          "abstencao": [],
          "ausente": [],
          "contrario": [],
          "favoravel": [],
          "presidencia": []
        }
      ]
    },
    {
      "@id": "/@@materias/204514",
      "@type": "Materia",
      "abstencao": 0,
      "apuracao": [],
      "ausente": 0,
      "autoria": [
        {
          "description": "Parlamentar",
          "id": "399022",
          "primeiro_autor": true,
          "title": "Liza Prado"
        }
      ],
      "contrario": 0,
      "description": "ALTERA A LEI Nº 14.097, DE 31 DE OUTUBRO DE 2023, QUE \"DISPENSA ÀS PESSOAS ACOMETIDAS PELA FIBROMIALGIA QUE SE ENQUADRE NO CONCEITO DE PESSOA COM DEFICIÊNCIA O MESMO TRATAMENTO DISPOSTO NA LEI FEDERAL 10.048, DE 08 DE NOVEMBRO DE 2000\".",
      "favoravel": 0,
      "id": "204514",
      "presidencia": 0,
      "quorum": "Maioria qualificada - 2/3",
      "tipo_votacao": "Nominal",
      "title": "Projeto de Lei Ordinária nº 46/2025",
      "turno": "Apreciar parecer contrário",
      "votos": [
        {
          "abstencao": [],
          "ausente": [],
          "contrario": [],
          "favoravel": [],
          "presidencia": []
        }
      ]
    },
    {
      "@id": "/@@materias/204516",
      "@type": "Materia",
      "abstencao": 0,
      "apuracao": [],
      "ausente": 0,
      "autoria": [
        {
          "description": "Parlamentar",
          "id": "399022",
          "primeiro_autor": true,
          "title": "Liza Prado"
        }
      ],
      "contrario": 0,
      "description": "ALTERA DISPOSITIVO DA LEI Nº 10.715, DE 21 DE MARÇO DE 2011, QUE \"INSTITUI O CÓDIGO MUNICIPAL DE SAÚDE\".",
      "favoravel": 0,
      "id": "204516",
      "presidencia": 0,
      "quorum": "Maioria qualificada - 2/3",
      "tipo_votacao": "Nominal",
      "title": "Projeto de Lei Ordinária nº 48/2025",
      "turno": "Apreciar parecer contrário",
      "votos": [
        {
          "abstencao": [],
          "ausente": [],
          "contrario": [],
          "favoravel": [],
          "presidencia": []
        }
      ]
    },
    {
      "@id": "/@@materias/204517",
      "@type": "Materia",
      "abstencao": 0,
      "apuracao": [],
      "ausente": 0,
      "autoria": [
        {
          "description": "Parlamentar",
          "id": "399022",
          "primeiro_autor": true,
          "title": "Liza Prado"
        }
      ],
      "contrario": 0,
      "description": "ESTABELECE A POLÍTICA MUNICIPAL DE PROTEÇÃO DOS DIREITOS DA PESSOA COM TRANSTORNO DO DESENVOLVIMENTO DA LINGUAGEM (TDL)",
      "favoravel": 0,
      "id": "204517",
      "presidencia": 0,
      "quorum": "Maioria qualificada - 2/3",
      "tipo_votacao": "Nominal",
      "title": "Projeto de Lei Ordinária nº 49/2025",
      "turno": "Apreciar parecer contrário",
      "votos": [
        {
          "abstencao": [],
          "ausente": [],
          "contrario": [],
          "favoravel": [],
          "presidencia": []
        }
      ]
    },
    {
      "@id": "/@@materias/204522",
      "@type": "Materia",
      "abstencao": 0,
      "apuracao": [],
      "ausente": 0,
      "autoria": [
        {
          "description": "Parlamentar",
          "id": "399022",
          "primeiro_autor": true,
          "title": "Liza Prado"
        }
      ],
      "contrario": 0,
      "description": "DISPÕE SOBRE A SUBSTITUIÇÃO DE SIRENES E ALARMES UTILIZADOS COMO SINALIZADORES DE INÍCIO E TÉRMINO DE AULAS, DE PROVAS E DE PERÍODO DE RECREIO NOS ESTABELECIMENTOS DAS REDES PÚBLICA E PRIVADA DE ENSINO NO MUNICÍPIO DE UBERLÂNDIA.",
      "favoravel": 0,
      "id": "204522",
      "presidencia": 0,
      "quorum": "Maioria qualificada - 2/3",
      "tipo_votacao": "Nominal",
      "title": "Projeto de Lei Ordinária nº 54/2025",
      "turno": "Apreciar parecer contrário",
      "votos": [
        {
          "abstencao": [],
          "ausente": [],
          "contrario": [],
          "favoravel": [],
          "presidencia": []
        }
      ]
    }
  ],
  "title": "Lista de votação nominal"
}